slacktory/__init__.py
slacktory-1.0.5.dist-info/LICENSE
slacktory-1.0.5.dist-info/METADATA
slacktory-1.0.5.dist-info/WHEEL
slacktory-1.0.5.dist-info/top_level.txt
slacktory-1.0.5.dist-info/RECORD
