Metadata-Version: 2.1
Name: slacktory
Version: 1.0.5
Summary: Simple Slack interface
Home-page: UNKNOWN
Author: James Coleman
Author-email: jamescoleman@me.com
License: MIT
Platform: UNKNOWN
Classifier: License :: OSI Approved :: MIT License
Classifier: Programming Language :: Python :: 3
Classifier: Programming Language :: Python :: 3.7
